mdpertool/__main__.py
mdpertool/_version.py
mdpertool/ui_main.py
mdpertool/Download/1aki.pdb
mdpertool/Download/2j0w_example.pdb
mdpertool/Download/2j0w_example_fixed_ph7.4.pdb
mdpertool/Download/2j0x.pdb
mdpertool/analysis/2d_network.html
mdpertool/analysis/VisJS_Widget.py
mdpertool/analysis/createRNetwork.py
mdpertool/analysis/example.gml
mdpertool/analysis/multiproc_net_calc.py
mdpertool/analysis/pdbsum_conservation_puller.py
mdpertool/fonts/segoeui.ttf
mdpertool/fonts/segoeuib.ttf
mdpertool/gui/MAIN_GUI.ui
mdpertool/gui/__init__.py
mdpertool/gui/big_icons.qrc
mdpertool/gui/files.qrc
mdpertool/gui/files_rc.py
mdpertool/gui/gifs.qrc
mdpertool/gui/icons.py
mdpertool/gui/icons_path.qrc
mdpertool/gui/splash_screen.ui
mdpertool/gui/ui_styles.py
mdpertool/no_gui/Classic_MD.py
mdpertool/no_gui/MD_1.py
mdpertool/no_gui/MD_2.py
mdpertool/no_gui/Run_Model.py
mdpertool/no_gui/Velocity_Changer.py
mdpertool/no_gui/__init__.py
mdpertool/no_gui/apply_pdbfixer.py
mdpertool/no_gui/divide_pdb.py
mdpertool/no_gui/energy_component.py
mdpertool/no_gui/energy_decomposition_from_trajectory.py
mdpertool/no_gui/example.txt
mdpertool/no_gui/get_positions_from_trajectory_file.py
mdpertool/no_gui/no_gui.py
mdpertool/no_gui/omm_units.py
mdpertool/no_gui/optimizepme.py
mdpertool/no_gui/pdb_trajectory_parser.py
mdpertool/no_gui/response_time_creator.py
mdpertool/no_gui/response_time_graph_creator.py
mdpertool/no_gui/write_outputs.py
mdpertool/src/CustomReporters.py
mdpertool/src/PyMolWidget.py
mdpertool/src/PyMol_PySide2.py
mdpertool/src/app_functions.py
mdpertool/src/apply_pdbfixer.py
mdpertool/src/browse_menu.py
mdpertool/src/builder.py
mdpertool/src/checkBox_menu.py
mdpertool/src/config.py
mdpertool/src/file_dialog.py
mdpertool/src/logger.py
mdpertool/src/message.py
mdpertool/src/mplwidget.py
mdpertool/src/omm_runner.py
mdpertool/src/pdb_intro_1aki.py
mdpertool/src/pyside_dynamic.py
mdpertool/src/template_script.txt
mdpertool/src/template_script_ori.txt
mdpertool/src/ui_functions.py
mdpertool-0.0.1.dev3.dist-info/LICENSE.md
mdpertool-0.0.1.dev3.dist-info/METADATA
mdpertool-0.0.1.dev3.dist-info/WHEEL
mdpertool-0.0.1.dev3.dist-info/entry_points.txt
mdpertool-0.0.1.dev3.dist-info/top_level.txt
mdpertool-0.0.1.dev3.dist-info/RECORD
